fastflight/__init__.py
fastflight/cli.py
fastflight/client.py
fastflight/exceptions.py
fastflight/server.py
fastflight/core/__init__.py
fastflight/core/base.py
fastflight/demo_services/__init__.py
fastflight/demo_services/echo_demo.py
fastflight/fastapi_integration/README.md
fastflight/fastapi_integration/__init__.py
fastflight/fastapi_integration/app.py
fastflight/fastapi_integration/dependencies.py
fastflight/fastapi_integration/lifespan.py
fastflight/fastapi_integration/router.py
fastflight/resilience/README.md
fastflight/resilience/__init__.py
fastflight/resilience/types.py
fastflight/resilience/config/__init__.py
fastflight/resilience/config/circuit_breaker.py
fastflight/resilience/config/resilience.py
fastflight/resilience/config/retry.py
fastflight/resilience/config_builder/__init__.py
fastflight/resilience/config_builder/builder.py
fastflight/resilience/config_builder/factory.py
fastflight/resilience/config_builder/types.py
fastflight/resilience/core/__init__.py
fastflight/resilience/core/circuit_breaker.py
fastflight/resilience/core/manager.py
fastflight/utils/__init__.py
fastflight/utils/custom_logging.py
fastflight/utils/debug.py
fastflight/utils/registry_check.py
fastflight/utils/stream_utils.py
fastflight-0.4.2.dist-info/METADATA
fastflight-0.4.2.dist-info/WHEEL
fastflight-0.4.2.dist-info/entry_points.txt
fastflight-0.4.2.dist-info/licenses/LICENSE
fastflight-0.4.2.dist-info/RECORD
