Metadata-Version: 2.4
Name: fastflight
Version: 0.4.2
Summary: FastFlight is a high-performance data transfer framework that integrates Apache Arrow Flight to fetch and stream large-scale data from multiple sources, using a modular, pluggable architecture for various data services, and offers optional FastAPI integration for HTTP-based access.
Author-email: Chao Ning <chao.ning.uk@gmail.com>
License-File: LICENSE
Requires-Python: >=3.10
Requires-Dist: pandas
Requires-Dist: pyarrow>=14
Requires-Dist: pydantic>=2.0
Requires-Dist: typing-extensions>=4.5.0
Provides-Extra: all
Requires-Dist: duckdb; extra == 'all'
Requires-Dist: fastapi[standard]; extra == 'all'
Requires-Dist: httpx; extra == 'all'
Requires-Dist: matplotlib>=3.10.1; extra == 'all'
Requires-Dist: rich; extra == 'all'
Requires-Dist: seaborn>=0.13.2; extra == 'all'
Requires-Dist: sqlalchemy>=2.0.38; extra == 'all'
Requires-Dist: structlog; extra == 'all'
Requires-Dist: typer>=0.15.2; extra == 'all'
Provides-Extra: cli
Requires-Dist: typer>=0.15.2; extra == 'cli'
Provides-Extra: examples
Requires-Dist: duckdb; extra == 'examples'
Requires-Dist: httpx; extra == 'examples'
Requires-Dist: matplotlib>=3.10.1; extra == 'examples'
Requires-Dist: rich; extra == 'examples'
Requires-Dist: seaborn>=0.13.2; extra == 'examples'
Requires-Dist: sqlalchemy>=2.0.38; extra == 'examples'
Provides-Extra: fastapi
Requires-Dist: fastapi[standard]; extra == 'fastapi'
Provides-Extra: structlog
Requires-Dist: structlog; extra == 'structlog'
